perceptron_vb/__init__.py
perceptron_vb/perceptron.py
utils/__init__.py
utils/all_utils.py
Perceptron_pypi_vishalbansal_1650-0.0.5.dist-info/LICENSE
Perceptron_pypi_vishalbansal_1650-0.0.5.dist-info/METADATA
Perceptron_pypi_vishalbansal_1650-0.0.5.dist-info/WHEEL
Perceptron_pypi_vishalbansal_1650-0.0.5.dist-info/top_level.txt
Perceptron_pypi_vishalbansal_1650-0.0.5.dist-info/RECORD
