Metadata-Version: 2.1
Name: Perceptron-pypi-vishalbansal-1650
Version: 0.0.5
Summary: It is an implmentation of perceptron
Home-page: https://github.com/vishalbansal-1650/Perceptron_pypi
Author: vishalbansal-1650
Author-email: vishalbansal1650@gmail.com
License: UNKNOWN
Project-URL: Bug Tracker, https://github.com/vishalbansal-1650/Perceptron_pypi/issues
Platform: UNKNOWN
Classifier: Programming Language :: Python :: 3
Classifier: License :: OSI Approved :: MIT License
Classifier: Operating System :: OS Independent
Requires-Python: >=3.7
License-File: LICENSE
Requires-Dist: numpy
Requires-Dist: tqdm
Requires-Dist: os
Requires-Dist: matplotlib
Requires-Dist: joblib
